db_analytics_tools/__init__.py
db_analytics_tools/airflow.py
db_analytics_tools/analytics.py
db_analytics_tools/integration.py
db_analytics_tools/learning.py
db_analytics_tools/mail.py
db_analytics_tools/plotting.py
db_analytics_tools/utils.py
db_analytics_tools/webapp.py
db_analytics_tools-0.1.8.6.dist-info/licenses/LICENSE
db_analytics_tools-0.1.8.6.dist-info/METADATA
db_analytics_tools-0.1.8.6.dist-info/WHEEL
db_analytics_tools-0.1.8.6.dist-info/entry_points.txt
db_analytics_tools-0.1.8.6.dist-info/top_level.txt
db_analytics_tools-0.1.8.6.dist-info/RECORD
