Metadata-Version: 2.4
Name: db_analytics_tools
Version: 0.1.8.6
Summary: Databases Tools for Data Analytics
Home-page: https://joekakone.github.io/#projects
Download-URL: https://github.com/joekakone/db-analytics-tools
Author: Joseph Konka
Author-email: joseph.kakone@gmail.com
License: MIT
Project-URL: Bug Tracker, https://github.com/joekakone/db-analytics-tools/issues
Project-URL: Documentation, https://joekakone.github.io/db-analytics-tools
Project-URL: Source Code, https://github.com/joekakone/db-analytics-tools
Keywords: databases analytics etl sql orc
Requires-Python: >=3.10
License-File: LICENSE
Requires-Dist: psycopg2-binary>=2.9.9
Requires-Dist: pyodbc>=5.1.0
Requires-Dist: pandas>=2.2.1
Requires-Dist: SQLAlchemy>=2.0.29
Requires-Dist: streamlit>=1.32.2
Requires-Dist: matplotlib>=3.4.3
Requires-Dist: statsmodels>=0.13.5
Dynamic: author
Dynamic: author-email
Dynamic: description
Dynamic: description-content-type
Dynamic: download-url
Dynamic: home-page
Dynamic: keywords
Dynamic: license
Dynamic: license-file
Dynamic: project-url
Dynamic: requires-dist
Dynamic: requires-python
Dynamic: summary
